[{"id":580,"name":"Adventurer"},{"id":585,"name":"Altul"},{"id":570,"name":"America"},{"id":565,"name":"Bonneville"},{"id":573,"name":"Daytona"},{"id":584,"name":"Hurricane"},{"id":576,"name":"Rocket"},{"id":571,"name":"Rocket 3"},{"id":569,"name":"Scrambler"},{"id":578,"name":"Speed Four"},{"id":566,"name":"Speed Triple"},{"id":572,"name":"Speedmaster"},{"id":575,"name":"Sprint"},{"id":568,"name":"Thruxton"},{"id":567,"name":"Thunderbird"},{"id":574,"name":"Tiger"},{"id":581,"name":"Trident"},{"id":577,"name":"Trophy"},{"id":582,"name":"TSS"},{"id":583,"name":"TSX"},{"id":579,"name":"TT"}]