[
  { "id": 988, "name": "Allante" },
  { "id": 1001, "name": "Altul" },
  { "id": 989, "name": "ATS" },
  { "id": 2372, "name": "BLS" },
  { "id": 990, "name": "BTL" },
  { "id": 991, "name": "CT6" },
  { "id": 992, "name": "CTS" },
  { "id": 993, "name": "Deville" },
  { "id": 994, "name": "Eldorado" },
  { "id": 995, "name": "Escalade" },
  { "id": 996, "name": "Fleetwood" },
  { "id": 2375, "name": "Other" },
  { "id": 997, "name": "Seville" },
  { "id": 998, "name": "SRX" },
  { "id": 999, "name": "STS" },
  { "id": 1000, "name": "XLR" },
  { "id": 2373, "name": "XT4" },
  { "id": 2374, "name": "XT5" }
]
