[{"id":1291,"name":"Accord"},{"id":2476,"name":"Aerodeck"},{"id":1311,"name":"Altul"},{"id":1292,"name":"City"},{"id":1293,"name":"Civic"},{"id":2477,"name":"Clarity"},{"id":2478,"name":"Concerto"},{"id":1294,"name":"CRV"},{"id":1295,"name":"CRX"},{"id":1296,"name":"CRZ"},{"id":2479,"name":"e"},{"id":2480,"name":"Element"},{"id":1297,"name":"FRV"},{"id":1298,"name":"HRV"},{"id":1299,"name":"Insight"},{"id":1300,"name":"Integra"},{"id":1301,"name":"Jazz"},{"id":1302,"name":"Legend"},{"id":1303,"name":"Logo"},{"id":1304,"name":"NSX"},{"id":1305,"name":"Odyssey"},{"id":2482,"name":"Other"},{"id":2481,"name":"Pilot"},{"id":1306,"name":"Prelude"},{"id":1307,"name":"Ridgeline"},{"id":1308,"name":"S2000"},{"id":1309,"name":"Shuttle"},{"id":1310,"name":"Stream"}]