[{"id":514,"name":"Altul"},{"id":498,"name":"Audace"},{"id":507,"name":"Bellagio"},{"id":504,"name":"Breva"},{"id":499,"name":"California"},{"id":511,"name":"Coppa Italia"},{"id":500,"name":"Eldorado"},{"id":501,"name":"Griso"},{"id":510,"name":"Mans"},{"id":505,"name":"MGS-01 Corsa"},{"id":494,"name":"MGX"},{"id":503,"name":"Nevada"},{"id":502,"name":"Norge"},{"id":512,"name":"Quota"},{"id":506,"name":"Sport"},{"id":495,"name":"Stelvio"},{"id":513,"name":"Targa"},{"id":508,"name":"V"},{"id":509,"name":"V 11"},{"id":496,"name":"V 7"},{"id":497,"name":"V 9"}]