[{"id":1365,"name":"Altul"},{"id":1348,"name":"EX30"},{"id":1349,"name":"EX35"},{"id":1350,"name":"EX37"},{"id":1351,"name":"FX"},{"id":1352,"name":"G35"},{"id":1353,"name":"G37"},{"id":1354,"name":"M30"},{"id":1355,"name":"M35"},{"id":1356,"name":"M37"},{"id":2497,"name":"Other"},{"id":1357,"name":"Q30"},{"id":1358,"name":"Q45"},{"id":1359,"name":"Q50"},{"id":1360,"name":"Q60"},{"id":1361,"name":"Q70"},{"id":2496,"name":"QX30"},{"id":1362,"name":"QX50"},{"id":1363,"name":"QX56"},{"id":1364,"name":"QX70"}]